weather_app/__init__.py
weather_app/__main__.py
weather_app/weather_client.py
weather_app/weather_client_detail.py
weather_app/weather_server.py
weather_app/weather_server_detail.py
weather_app_feifei-1.0.3.dist-info/METADATA
weather_app_feifei-1.0.3.dist-info/WHEEL
weather_app_feifei-1.0.3.dist-info/entry_points.txt
weather_app_feifei-1.0.3.dist-info/top_level.txt
weather_app_feifei-1.0.3.dist-info/RECORD
