Metadata-Version: 2.4
Name: weather-app-feifei
Version: 1.0.3
Summary: 基于MCP框架的天气查询应用，包含客户端和服务器组件
Author-email: Feifei <feifei@example.com>
License: MIT
Project-URL: Homepage, https://github.com/feifei/weather-app
Project-URL: Repository, https://github.com/feifei/weather-app
Project-URL: Documentation, https://github.com/feifei/weather-app/blob/main/README.md
Project-URL: Issues, https://github.com/feifei/weather-app/issues
Keywords: weather,mcp,api,client-server,openweather
Classifier: Development Status :: 4 - Beta
Classifier: Programming Language :: Python :: 3
Classifier: Programming Language :: Python :: 3.13
Classifier: Operating System :: OS Independent
Classifier: Intended Audience :: Developers
Classifier: Topic :: Software Development :: Libraries :: Python Modules
Classifier: Topic :: Scientific/Engineering :: Atmospheric Science
Classifier: Topic :: Internet :: WWW/HTTP :: Indexing/Search
Requires-Python: >=3.13
Requires-Dist: httpx>=0.28.1
Requires-Dist: mcp>=1.17.0
Requires-Dist: python-dotenv>=1.1.1
Requires-Dist: openai>=1.30.0
